pipasic_src/PASiC.py
pipasic_src/TideProcessing.py
pipasic_src/__init__.py
pipasic_src/inspectparser.py
pipasic_src/pipasic.py
pipasic_src/plotting.py
pipasic_src/readMGF.py
pipasic_src/runInspect_user_config.py
pipasic_src/simulation_based_similarity.py
pipasic_src/trypticpeptides.py
pipasic_src/config_files/config_Inspect_MSSim.txt
pipasic_src/config_files/config_Inspect_MSSim_py.txt
pipasic_src/config_files/config_Inspect_py.txt
pipasic_src/config_files/config_MSSim_v1_9_short.ini
pipasic_src/config_files/song.txt
pipasic_src/inspect/.DS_Store
pipasic_src/inspect/AdjustPTM.py
pipasic_src/inspect/AminoAcidMasses.txt
pipasic_src/inspect/BasicStats.py
pipasic_src/inspect/BuildConsensusSpectrum.py
pipasic_src/inspect/BuildInspect.py
pipasic_src/inspect/BuildMGF.py
pipasic_src/inspect/CCSVM1.model
pipasic_src/inspect/CCSVM1.range
pipasic_src/inspect/CCSVM2.model
pipasic_src/inspect/CCSVM2.range
pipasic_src/inspect/CCSVM2Phos.model
pipasic_src/inspect/CCSVM2Phos.range
pipasic_src/inspect/Ch2BNPEP.dat
pipasic_src/inspect/Ch2BNPEPQ.dat
pipasic_src/inspect/Ch3BNPEP.dat
pipasic_src/inspect/Ch3BNPEPQ.dat
pipasic_src/inspect/CombinePTMFeatures.py
pipasic_src/inspect/CompareHEKPTM.py
pipasic_src/inspect/ComputeFScore.py
pipasic_src/inspect/ComputePTMFeatures.py
pipasic_src/inspect/ExplainPTMs.py
pipasic_src/inspect/FDRUtils.py
pipasic_src/inspect/GetByteOffset.py
pipasic_src/inspect/Global.py
pipasic_src/inspect/InVitroModifications.txt
pipasic_src/inspect/InVivoModifications.txt
pipasic_src/inspect/Inspect.exe
pipasic_src/inspect/Inspect.sln
pipasic_src/inspect/Inspect.vcproj
pipasic_src/inspect/InspectToPepXML.py
pipasic_src/inspect/IsotopePatterns.txt
pipasic_src/inspect/LDA.py
pipasic_src/inspect/Label.py
pipasic_src/inspect/Learning.py
pipasic_src/inspect/MQScoreLDA2.model
pipasic_src/inspect/MQScoreLDA3.model
pipasic_src/inspect/MQScoreSVM2.model
pipasic_src/inspect/MQScoreSVM2.range
pipasic_src/inspect/MQScoreSVM3.model
pipasic_src/inspect/MQScoreSVM3.range
pipasic-1.6.dist-info/LICENSE
pipasic-1.6.dist-info/METADATA
pipasic-1.6.dist-info/WHEEL
pipasic-1.6.dist-info/entry_points.txt
pipasic-1.6.dist-info/top_level.txt
pipasic-1.6.dist-info/RECORD
